Metadata-Version: 2.1
Name: gryszka-hello-package
Version: 0.1.4
Summary: Testing WHL purpose. Hello World
Home-page: https://github.com/Gryszka/public_nested_packages/src/gryszka_hello_package
Author: Gryszka
Author-email: romanowicz.g@gmail.com
License: Apache License 2.0
Keywords: testing example package
Platform: UNKNOWN
Classifier: Programming Language :: Python :: 3
Classifier: License :: OSI Approved :: Apache Software License
Classifier: Operating System :: OS Independent
Requires-Dist: gryszka-another-package
